py_deprecate/__init__.py
py_deprecate/decorate.py
py_deprecate/exceptions.py
py_deprecate/settings.py
py_deprecate/behaviors/__init__.py
py_deprecate/behaviors/base.py
py_deprecate/behaviors/disabled.py
py_deprecate/behaviors/log.py
py_deprecate/behaviors/raise_exception.py
tests/__init__.py
tests/fixtures.py
tests/test_decorator.py
py_deprecate-0.0.4.dist-info/LICENSE
py_deprecate-0.0.4.dist-info/METADATA
py_deprecate-0.0.4.dist-info/WHEEL
py_deprecate-0.0.4.dist-info/top_level.txt
py_deprecate-0.0.4.dist-info/RECORD
