Metadata-Version: 2.1
Name: py-deprecate
Version: 0.0.4
Summary: Python Deprecation Toolkit
Home-page: https://github.com/multi-vac/py_deprecate
Author: multi-vac
Author-email: multivac_7@protonmail.com
License: UNKNOWN
Project-URL: Bug Tracker, https://github.com/multi-vac/py_deprecate/issues
Platform: UNKNOWN
Classifier: Programming Language :: Python :: 3
Classifier: License :: OSI Approved :: MIT License
Classifier: Operating System :: OS Independent
Requires-Python: >=3.5
